scurri_zipcode/__init__.py
scurri_zipcode/exceptions.py
scurri_zipcode/functions.py
scurri_zipcode/utils.py
scurri_zipcode/validators.py
scurri_zipcode-0.1.5.dist-info/METADATA
scurri_zipcode-0.1.5.dist-info/WHEEL
scurri_zipcode-0.1.5.dist-info/top_level.txt
scurri_zipcode-0.1.5.dist-info/RECORD
