Metadata-Version: 2.1
Name: scurri-zipcode
Version: 0.1.5
Summary: Python library to validate zip codes in the UK for Scurri interview
Home-page: https://github.com/JuliColombo/scurri-zipcode
Author: Julieta Colombo
License: MIT
Platform: UNKNOWN
